LICENSE.txt
README.md
setup.py
Metaplex.egg-info/PKG-INFO
Metaplex.egg-info/SOURCES.txt
Metaplex.egg-info/dependency_links.txt
Metaplex.egg-info/entry_points.txt
Metaplex.egg-info/requires.txt
Metaplex.egg-info/top_level.txt
metaplex/__init__.py
metaplex/index_jump.py
metaplex/length_filtering.py
metaplex/per_sample_filtering.py
metaplex/remultiplexing.py