Metadata-Version: 2.1
Name: Metaplex
Version: 1.0.0
Summary: Read Processing and Quality Control Toolkit for Dual-Indexed Metabarcoding
Home-page: https://github.com/NGabry/MetaPlex
Author: Nick Gabry
Author-email: n.t.gabry@gmail.com
License: BSD 3-clause
Platform: UNKNOWN
Classifier: Development Status :: 5 - Production/Stable
Classifier: Intended Audience :: Science/Research
Classifier: License :: OSI Approved :: BSD License
Classifier: Operating System :: Unix
Classifier: Programming Language :: Python :: 3 :: Only
Classifier: Topic :: Scientific/Engineering :: Bio-Informatics
License-File: LICENSE.txt
